eparkhontos/__init__.py
eparkhontos/__version__.py
eparkhontos/eparkhontos.py
eparkhontos-0.0.1.dist-info/LICENSE
eparkhontos-0.0.1.dist-info/METADATA
eparkhontos-0.0.1.dist-info/WHEEL
eparkhontos-0.0.1.dist-info/top_level.txt
eparkhontos-0.0.1.dist-info/RECORD
