Metadata-Version: 2.1
Name: eparkhontos
Version: 0.0.1
Summary: Parse and convert ancient Greek archon dates
Home-page: https://github.com/seanredmond/eparkhontos
Author: Sean Redmond
Author-email: github-smr@sneakemail.com
Project-URL: Bug Tracker, https://github.com/seanredmond/eparkhontos/issues
Classifier: Programming Language :: Python :: 3
Classifier: License :: OSI Approved :: GNU General Public License v3 or later (GPLv3+)
Classifier: Operating System :: OS Independent
Requires-Python: >=3.8
License-File: LICENSE
